PyAsynch-1.2.2.dist-info/METADATA
PyAsynch-1.2.2.dist-info/RECORD
PyAsynch-1.2.2.dist-info/WHEEL
PyAsynch-1.2.2.dist-info/top_level.txt
pyasynch/__init__.py
pyasynch/encoder.py
pyasynch/endpoint.py
pyasynch/environment.py
pyasynch/main.py
pyasynch/node.py
pyasynch/option.py
