Metadata-Version: 2.1
Name: PyAsynch
Version: 1.2.2
Summary: Python asynch distributed and scalable Queue Services
Home-page: https://github.com/hoploop/pyasynch
Author: Roberto Forlani
Author-email: roberto.forlani@gmail.com
License: UNKNOWN
Platform: UNKNOWN
Requires-Dist: pika
Requires-Dist: python-dateutil
Requires-Dist: tornado
